vrun/__init__.py
vrun/__main__.py
vrun/cli.py
vrun/compat.py
vrun/config.py
vrun/oscompat.py
vrun-0.4.dist-info/DESCRIPTION.rst
vrun-0.4.dist-info/LICENSE.txt
vrun-0.4.dist-info/METADATA
vrun-0.4.dist-info/RECORD
vrun-0.4.dist-info/WHEEL
vrun-0.4.dist-info/entry_points.txt
vrun-0.4.dist-info/metadata.json
vrun-0.4.dist-info/top_level.txt
