Metadata-Version: 2.0
Name: vrun
Version: 0.4
Summary: Adds Python's bin/Scripts directory to PATH before executing a command. Primarily used with Python virtual environments.
Home-page: https://github.com/bertjwregeer/vrun
Author: Bert JW Regeer
Author-email: bertjw@regeer.org
License: ISC
Keywords: virtualenv vexec vrun venv bin Scripts
Platform: UNKNOWN
Classifier: Development Status :: 4 - Beta
Classifier: Intended Audience :: Developers
Classifier: License :: OSI Approved :: ISC License (ISCL)
Classifier: Natural Language :: English
Classifier: Programming Language :: Python :: 2
Classifier: Programming Language :: Python :: 2.7
Classifier: Programming Language :: Python :: 3
Classifier: Programming Language :: Python :: 3.4
Classifier: Programming Language :: Python :: 3.5
Classifier: Programming Language :: Python :: 3.6
Classifier: Programming Language :: Python :: Implementation :: CPython
Classifier: Programming Language :: Python :: Implementation :: PyPy
Requires-Python: >=2.7,!=3.0.*,!=3.1.*,!=3.2.*,!=3.3.*
Provides-Extra: docs
Requires-Dist: Sphinx; extra == 'docs'
Provides-Extra: testing
Requires-Dist: pytest; extra == 'testing'
Requires-Dist: pytest-cov; extra == 'testing'
